icalstatus/__init__.py
icalstatus/date.py
icalstatus/parse.py
icalstatus/retry.py
icalstatus/status.py
icalstatus-0.1.0.dist-info/METADATA
icalstatus-0.1.0.dist-info/WHEEL
icalstatus-0.1.0.dist-info/entry_points.txt
icalstatus-0.1.0.dist-info/licenses/LICENSE
icalstatus-0.1.0.dist-info/RECORD
