Metadata-Version: 2.4
Name: icalstatus
Version: 0.1.0
Summary: icalstatus
Project-URL: Homepage, https://github.com/frbor/icalstatus
Author-email: Fredrik Borg <fredrikb.borg@gmail.com>
License-Expression: ISC
License-File: LICENSE
Classifier: Development Status :: 4 - Beta
Classifier: License :: OSI Approved :: ISC License (ISCL)
Classifier: Topic :: Utilities
Requires-Python: >=3.12
Requires-Dist: caep<2,>=1.3.0
Requires-Dist: icalendar<7,>=6.0.0
Requires-Dist: recurring-ical-events<4,>=3.5.2
Requires-Dist: requests<3,>=2.31.0
